Workbook

Sheet Dashboard
A1: DOMME × LASZLO
A2: Motor de Precificação v3 — Perfeição Operacional
A4: 📊 KPIs DO ECOSSISTEMA
A5: Total SKUs no Catálogo | B5: 589
A6: SKUs Disponíveis para White Label | B6: 491
A7: SKUs em Risco de Estoque | B7: 98
A8: SKUs em Retirada de Linha | B8: 0
A9: Matérias-Primas Cadastradas | B9: 2583
A10: Ticket Médio Geral Laszlo (R$) | B10: 58
A11: Fee DOMME por Projeto (R$) | B11: 1500
A13: 🗂️ NAVEGAÇÃO DAS ABAS
A14: ➤ Motor v3 | B14: Simulador principal — insira SKU, lote e preço
A15: ➤ Cenários | B15: Comparativo de escala (Tier 1 vs Tier 2 vs Tier 3)
A16: ➤ Exportação | B16: Módulo internacional — USD/EUR com markup 8x
A17: ➤ Proposta | B17: Layout PDF-ready para envio ao cliente
A18: ➤ Catálogo Laszlo | B18: 589 SKUs com status WL e benchmarks
A19: ➤ Base cadastro MP | B19: 2583 matérias-primas com custo real
A20: ➤ Check_Retirada | B20: 48 produtos em descontinuação
A21: ➤ Parâmetros v3 | B21: Margens, tiers, fees e regras editáveis
A22: ➤ Regras v3 | B22: Documentação completa das regras de negócio
A24: ⚠️ NOTAS IMPORTANTES
A25: 1. Desconto de 15% no ROI é conservador. Em marketplaces (ML, Shopee), taxas chegam a 18-22%.
A26: 2. Templates técnicos: verso (dados legais) é IMUTÁVEL. Design exclusivo é serviço à parte.
A27: 3. Foco regulatório: Aromas Naturais / Alimentos para rapidez de mercado.
A28: 4. Células AZUIS são editáveis. Células PRETAS são fórmulas — não altere.

Sheet Motor v3
A1: DOMME × LASZLO — SIMULADOR v3
A2: Precificação por Lote · Full-Service · Métricas de Sucesso
A4: ▸ ENTRADA DO CLIENTE
A6: SKU (selecione do catálogo) | B6: ABS ALGAS-MARINHAS 10 GT FRANCA 10ML | C6: Menu suspenso ↓
A7: Volume por Lote (unidades) | B7: 200 | C7: Qtd produzida de uma só vez
A8: Preço de Venda ao Consumidor (R$) | C8: Se vazio, usa Varejo Laszlo
A9: Mercado | B9: Brasil | C9: Brasil / Internacional
A11: ▸ DADOS DO PRODUTO (automático via catálogo)
A13: Código Laszlo | B13: =IFERROR(VLOOKUP(B6,'Catálogo Laszlo'!A:I,2,FALSE()),"—") -> 1124 | C13: PROCV automático
A14: CVU Matéria-Prima (R$) | B14: =IFERROR(VLOOKUP(B6,'Catálogo Laszlo'!A:I,3,FALSE()),0) -> 46.145535 | C14: Custo unitário real da fábrica
A15: Ticket Médio Vendas Laszlo (R$) | B15: =IFERROR(VLOOKUP(B6,'Catálogo Laszlo'!A:I,4,FALSE()),0) -> 167.47941 | C15: Benchmark de mercado
A16: Volume do Frasco (ml) | B16: =IFERROR(VLOOKUP(B6,'Catálogo Laszlo'!A:I,9,FALSE()),10) -> 10 | C16: Extraído do nome
A17: Status WL do Produto | B17: =IFERROR(VLOOKUP(B6,'Catálogo Laszlo'!A:I,8,FALSE()),"—") -> ✓ Disponível | C17: Verifica disponibilidade
A19: ▸ INTELIGÊNCIA DE CUSTOS (Full-Service)
A21: Kit de Envase Base (frasco+tampa+got.) R$ | B21: 2.5 | C21: Custo base unitário do kit
A22: Fator de Escala Insumos | B22: =IF(B7<=100,2,1) -> 1 | C22: Lote ≤100: 2x | >100: 1x
A23: Custo Envase Ajustado (R$) | B23: =B21*B22 -> 2.5 | C23: Kit × Fator de Escala
A24: CVU Total (MP + Envase) | B24: =B14+B23 -> 48.645535
A25: Fee DOMME Rateado (R$1.500 ÷ Lote) | B25: =IF(B7>0,1500/B7,0) -> 7.5
A26: Custo Total Unitário c/ Fee (R$) | B26: =B24+B25 -> 56.145535
A28: ▸ DECOMPOSIÇÃO DE PREÇO
A30: MIL — Margem Industrial Laszlo | B30: 0.4 | C30: Mínimo 20% MC garantido
A31: PI Laszlo (= CVU Total × (1+MIL)) | B31: =B24*(1+B30) -> 68.103749
A32: MD — Margem Comercial DOMME | B32: 0.2
A33: Selo Laszlo | B33: 0.03
A34: Markup de Volume (auto por lote) | B34: =IF(B7<=500,0.2,IF(B7<=2000,0.1,0)) -> 0.2 | C34: T1≤500:20% | T2≤2000:10% | T3>2000:0%
A35: Tier Identificado | B35: =IF(B7<=500,"Tier 1 — Boutique",IF(B7<=2000,"Tier 2 — Growth","Tier 3 — Scale")) -> Tier 1 — Boutique
A36: PFC Unitário Brasil (R$) | B36: =B31*(1+B32)*(1+B34)*(1+B33) -> 101.01148 | C36: Preço Final ao Cliente DOMME
A37: PFC Export (se Internacional) | B37: =IF(B9="Internacional",B24*8,B36) -> 101.01148 | C37: Markup 8x para OEs no exterior
A38: PFC FINAL (R$) | B38: =IF(B9="Internacional",B37,B36) -> 101.01148 | C38: Auto: Brasil ou Export
A40: ▸ MÉTRICAS DE SUCESSO DO CLIENTE
A42: Preço de Venda Efetivo (R$) | B42: =IF(B8="",B15,B8) -> 167.47941 | C42: Usa input ou Ticket Médio Laszlo
A43: Índice de Viabilidade (IV) | B43: =IF(B15>0,B38/B15,"—") -> 0.60312775 | C43: PFC ÷ Varejo Laszlo (ideal < 0.55)
A44: Status IV | B44: =IF(B43="—","Sem dados",IF(B43<0.55,"✓ VIÁVEL — Proposta Saudável",IF(B43<=0.7,"⚠ ATENÇÃO — Margem Apertada","✗ CRÍTICO — Rever Custos"))) -> ⚠ ATENÇÃO — Margem Apertada
A45: Alerta Competitividade | B45: =IF(B42>B15*1.2,"⚠ Preço acima de 120% do benchmark","✓ Competitivo") -> ✓ Competitivo
A46: Investimento Inicial Total (R$) | B46: =B38*B7+1500 -> 21702.296 | C46: (PFC × Lote) + Fee
A47: Preço Venda Líquido (−15% imp/frete) | B47: =B42*0.85 -> 142.3575
A48: Margem Líquida por Unidade (R$) | B48: =B47-B38 -> 41.34602
A49: Break-Even Real (unidades) | B49: =IF(B48>0,ROUNDUP(B46/B48,0),"Inviável") -> 525 | C49: Unidades para cobrir investimento
A50: Lucro Líquido Projetado no Lote (R$) | B50: =IF(B48>0,B48*B7,0) -> 8269.2039
A51: ROI Líquido Conservador (%) | B51: =IF(B46>0,B50/B46,0) -> 0.38102899
A53: ▸ ALERTAS AUTOMÁTICOS
A55: 🚫 Produto em Retirada? | B55: =IF(ISNUMBER(SEARCH("Indisponível",B17)),"⛔ PRODUTO EM DESCONTINUAÇÃO — Cálculo bloqueado","✓ Produto ativo") -> ✓ Produto ativo
A56: 🏭 Margem Laszlo ≥ 20%? | B56: =IF(B24>0,IF((B31-B24)/B31>=0.2,"✓ Margem Laszlo protegida ("&TEXT((B31-B24)/B31,"0.0%")&")","⚠ MARGEM ABAIXO DE 20% — Revisar MIL"),"—") -> ✓ Margem Laszlo protegida (29%)
A57: 📦 Escala de Insumos Ativa? | B57: =IF(B22=2,"⚠ Fator 2x ativo — lote ≤100un","✓ Escala normal") -> ✓ Escala normal
A58: 💰 Viabilidade do Cliente | B58: =B44 -> ⚠ ATENÇÃO — Margem Apertada

Sheet Cenários
A1: ANÁLISE DE GANHO EM ESCALA — Simulador de Cenários
A2: "E se eu produzir mais?" — Comparativo automático de 3 cenários de lote
A3: Produto selecionado: | B3: ='Motor v3'!B6 -> ABS ALGAS-MARINHAS 10 GT FRANCA 10ML
A5: Métrica | B5: Cenário 1: 50 un | C5: Cenário 2: 200 un | D5: Cenário 3: 500 un | E5: Cenário 4: 1.000 un
A6: Tier | B6: ="Tier 1" -> Tier 1 | C6: ="Tier 1" -> Tier 1 | D6: ="Tier 1" -> Tier 1 | E6: ="Tier 2" -> Tier 2
A7: Markup Volume | B7: =0.2 -> 0.2 | C7: =0.2 -> 0.2 | D7: =0.2 -> 0.2 | E7: =0.1 -> 0.1
A8: Fator Escala Envase | B8: =2 -> 2 | C8: =1 -> 1 | D8: =1 -> 1 | E8: =1 -> 1
A9: Custo Envase Ajustado | B9: ='Motor v3'!B21*2 -> 5 | C9: ='Motor v3'!B21*1 -> 2.5 | D9: ='Motor v3'!B21*1 -> 2.5 | E9: ='Motor v3'!B21*1 -> 2.5
A10: CVU Total (MP+Envase) | B10: ='Motor v3'!B14+'Motor v3'!B21*2 -> 51.145535 | C10: ='Motor v3'!B14+'Motor v3'!B21 -> 48.645535 | D10: ='Motor v3'!B14+'Motor v3'!B21 -> 48.645535 | E10: ='Motor v3'!B14+'Motor v3'!B21 -> 48.645535
A11: Fee Rateado (R$) | B11: =1500/50 -> 30 | C11: =1500/200 -> 7.5 | D11: =1500/500 -> 3 | E11: =1500/1000 -> 1.5
A12: Custo Unit. c/ Fee (R$) | B12: =('Motor v3'!B14+'Motor v3'!B21*2)+1500/50 -> 81.145535 | C12: =('Motor v3'!B14+'Motor v3'!B21)+1500/200 -> 56.145535 | D12: =('Motor v3'!B14+'Motor v3'!B21)+1500/500 -> 51.645535 | E12: =('Motor v3'!B14+'Motor v3'!B21)+1500/1000 -> 50.145535
A13: PI Laszlo (R$) | B13: =('Motor v3'!B14+'Motor v3'!B21*2)*(1+'Motor v3'!B30) -> 71.603749 | C13: =('Motor v3'!B14+'Motor v3'!B21)*(1+'Motor v3'!B30) -> 68.103749 | D13: =('Motor v3'!B14+'Motor v3'!B21)*(1+'Motor v3'!B30) -> 68.103749 | E13: =('Motor v3'!B14+'Motor v3'!B21)*(1+'Motor v3'!B30) -> 68.103749
A14: PFC Unitário (R$) | B14: =('Motor v3'!B14+'Motor v3'!B21*2)*(1+'Motor v3'!B30)*(1+'Motor v3'!B32)*(1+0.2)*(1+'Motor v3'!B33) -> 106.20268 | C14: =('Motor v3'!B14+'Motor v3'!B21)*(1+'Motor v3'!B30)*(1+'Motor v3'!B32)*(1+0.2)*(1+'Motor v3'!B33) -> 101.01148 | D14: =('Motor v3'!B14+'Motor v3'!B21)*(1+'Motor v3'!B30)*(1+'Motor v3'!B32)*(1+0.2)*(1+'Motor v3'!B33) -> 101.01148 | E14: =('Motor v3'!B14+'Motor v3'!B21)*(1+'Motor v3'!B30)*(1+'Motor v3'!B32)*(1+0.1)*(1+'Motor v3'!B33) -> 92.593857
A15: Investimento Total (R$) | B15: =(('Motor v3'!B14+'Motor v3'!B21*2)*(1+'Motor v3'!B30)*(1+'Motor v3'!B32)*(1+0.2)*(1+'Motor v3'!B33))*50+1500 -> 6810.134 | C15: =(('Motor v3'!B14+'Motor v3'!B21)*(1+'Motor v3'!B30)*(1+'Motor v3'!B32)*(1+0.2)*(1+'Motor v3'!B33))*200+1500 -> 21702.296 | D15: =(('Motor v3'!B14+'Motor v3'!B21)*(1+'Motor v3'!B30)*(1+'Motor v3'!B32)*(1+0.2)*(1+'Motor v3'!B33))*500+1500 -> 52005.74 | E15: =(('Motor v3'!B14+'Motor v3'!B21)*(1+'Motor v3'!B30)*(1+'Motor v3'!B32)*(1+0.1)*(1+'Motor v3'!B33))*1000+1500 -> 94093.857
A16: Margem Líquida Unit. (R$) | B16: ='Motor v3'!B42*0.85-('Motor v3'!B14+'Motor v3'!B21*2)*(1+'Motor v3'!B30)*(1+'Motor v3'!B32)*(1+0.2)*(1+'Motor v3'!B33) -> 36.15482 | C16: ='Motor v3'!B42*0.85-('Motor v3'!B14+'Motor v3'!B21)*(1+'Motor v3'!B30)*(1+'Motor v3'!B32)*(1+0.2)*(1+'Motor v3'!B33) -> 41.34602 | D16: ='Motor v3'!B42*0.85-('Motor v3'!B14+'Motor v3'!B21)*(1+'Motor v3'!B30)*(1+'Motor v3'!B32)*(1+0.2)*(1+'Motor v3'!B33) -> 41.34602 | E16: ='Motor v3'!B42*0.85-('Motor v3'!B14+'Motor v3'!B21)*(1+'Motor v3'!B30)*(1+'Motor v3'!B32)*(1+0.1)*(1+'Motor v3'!B33) -> 49.763643
A17: Lucro Líquido Lote (R$) | B17: =('Motor v3'!B42*0.85-('Motor v3'!B14+'Motor v3'!B21*2)*(1+'Motor v3'!B30)*(1+'Motor v3'!B32)*(1+0.2)*(1+'Motor v3'!B33))*50 -> 1807.741 | C17: =('Motor v3'!B42*0.85-('Motor v3'!B14+'Motor v3'!B21)*(1+'Motor v3'!B30)*(1+'Motor v3'!B32)*(1+0.2)*(1+'Motor v3'!B33))*200 -> 8269.2039 | D17: =('Motor v3'!B42*0.85-('Motor v3'!B14+'Motor v3'!B21)*(1+'Motor v3'!B30)*(1+'Motor v3'!B32)*(1+0.2)*(1+'Motor v3'!B33))*500 -> 20673.01 | E17: =('Motor v3'!B42*0.85-('Motor v3'!B14+'Motor v3'!B21)*(1+'Motor v3'!B30)*(1+'Motor v3'!B32)*(1+0.1)*(1+'Motor v3'!B33))*1000 -> 49763.643
A19: 💡 INSIGHT: Ao aumentar o lote, o Fee rateado cai drasticamente e o lucro por unidade sobe.

Sheet Exportação
A1: MÓDULO DE EXPORTAÇÃO — WL Export
A3: ▸ COTAÇÕES (editável)
A5: Cotação USD → BRL | B5: 5.5 | C5: Edite conforme câmbio do dia
A6: Cotação EUR → BRL | B6: 5.9 | C6: Edite conforme câmbio do dia
A7: Frete Internacional Estimado (USD/un) | B7: 2 | C7: Custo estimado por unidade
A9: ▸ PRECIFICAÇÃO INTERNACIONAL
A11: Produto | B11: ='Motor v3'!B6 -> ABS ALGAS-MARINHAS 10 GT FRANCA 10ML
A12: CVU Total (R$) | B12: ='Motor v3'!B24 -> 48.645535
A13: PFC Export (Markup 8x, R$) | B13: ='Motor v3'!B24*8 -> 389.16428 | C13: Sem impostos internos (IPI/ICMS removidos)
A14: PFC Export (USD) | B14: =B13/B5 -> 70.757142
A15: PFC Export (EUR) | B15: =B13/B6 -> 65.960047
A16: PFC + Frete (USD) | B16: =B14+B7 -> 72.757142
A17: PFC + Frete (EUR) | B17: =B15+(B7*B5/B6) -> 67.824454
A19: ▸ NOTA: IPI e ICMS removidos. Produto segue como Aroma Natural/Alimento.

Sheet Proposta
A1: PROPOSTA COMERCIAL — WHITE LABEL
A2: DOMME × Laszlo Aromaterapia
A3: ────────────────────────────────────────────────────────────
A5: PRODUTO SELECIONADO
A7: Produto | B7: ='Motor v3'!B6 -> ABS ALGAS-MARINHAS 10 GT FRANCA 10ML
A8: Tier de Operação | B8: ='Motor v3'!B35 -> Tier 1 — Boutique
A9: Volume do Lote | B9: ='Motor v3'!B7 -> 200
A10: Mercado | B10: ='Motor v3'!B9 -> Brasil
A12: INVESTIMENTO DO CLIENTE
A14: Preço Unitário (PFC) | B14: ='Motor v3'!B38 -> 101.01148
A15: Fee de Estruturação DOMME | B15: =1500 -> 1500 | C15: One-time
A16: Investimento Total | B16: ='Motor v3'!B46 -> 21702.296
A18: RETORNO PROJETADO (Conservador)
A20: Preço de Venda Sugerido | B20: ='Motor v3'!B42 -> 167.47941
A21: Margem Líquida por Unidade | B21: ='Motor v3'!B48 -> 41.34602 | C21: Já descontado 15% (impostos+frete)
A22: Break-Even | B22: ='Motor v3'!B49 -> 525 | C22: Unidades para cobrir investimento
A23: Lucro Líquido no Lote | B23: ='Motor v3'!B50 -> 8269.2039
A24: ROI Conservador | B24: ='Motor v3'!B51 -> 0.38102899
A26: STATUS DE VIABILIDADE
A28: Índice de Viabilidade (IV) | B28: ='Motor v3'!B43 -> 0.60312775 | C28: Ideal < 0.55
A29: Diagnóstico | B29: ='Motor v3'!B44 -> ⚠ ATENÇÃO — Margem Apertada
A30: Competitividade | B30: ='Motor v3'!B45 -> ✓ Competitivo
A32: ────────────────────────────────────────────────────────────
A33: O que está incluído: Produto Laszlo padrão + Rótulo do cliente + Selo Laszlo
A34: Template técnico (verso): dados legais imutáveis. Design exclusivo: serviço à parte.
A35: Foco regulatório: Aromas Naturais / Alimentos para rapidez de mercado.
A37: DOMME — Inteligência em White Label

Sheet Catálogo Laszlo
A1: Nome do Produto | B1: Código | C1: CVU (R$) | D1: Ticket Médio (R$) | E1: Vendas 2024 | F1: Ranking | G1: % MC Real | H1: Status WL | I1: Volume (ml)
A2: ABS ALGAS-MARINHAS 10 GT FRANCA 10ML | B2: 1124 | C2: 46.145535 | D2: 167.47941 | E2: 34 | F2: 241 | G2: 0.2744704 | H2: ✓ Disponível | I2: 10
A3: ABS BAUNILHA 10 GT MADAGASCAR 10ML | B3: 707 | C3: 40.70176 | D3: 128.02336 | E3: 238 | F3: 71 | G3: 0.23207552 | H3: ✓ Disponível | I3: 10
A4: ABS BENJOIM-DO-SIAO GT LAOS 10ML | B4: 708 | C4: 9.36456 | D4: 43.6443 | E4: 486 | F4: 69 | G4: 0.33543453 | H4: ✓ Disponível | I4: 10
A5: ABS CACAU CHOCOLATE 30 GT FRANCA 10ML | B5: 968 | C5: 27.849811 | D5: 167.4 | E5: 10 | F5: 205 | G5: 0.38363315 | H5: ✓ Disponível | I5: 10
A6: ABS CACAU GT EUA 5ML | B6: 2184 | C6: 8.95709 | D6: 0 | E6: 0 | F6: NOVO | G6: 0 | H6: ⚠ Risco Estoque | I6: 5
A7: ABS JASMIM-SAMBAC 10 GT INDIA 10ML | B7: 1131 | C7: 32.42397 | D7: 174.3 | E7: 72 | F7: 121 | G7: 0.36397608 | H7: ✓ Disponível | I7: 10
A8: ABS LADANO CISTO GT ESPANHA 5ML | B8: 1119 | C8: 14.193 | D8: 75.712671 | E8: 161 | F8: 116 | G8: 0.36254128 | H8: ✓ Disponível | I8: 5
A9: ABS LAVANDIM GROSSO GT FRANCA 10ML | B9: 972 | C9: 15.26959 | D9: 0 | E9: 0 | F9: 456 | G9: 0 | H9: ⚠ Risco Estoque | I9: 10
A10: ABS MUSGO-DE-CARVALHO GT MACEDONIA 10ML | B10: 1374 | C10: 16.4426 | D10: 107.60769 | E10: 13 | F10: 207 | G10: 0.39719866 | H10: ✓ Disponível | I10: 10
A11: ABS SEMPRE-VIVA-DAS-AREIAS 10 GT ESPANHA 10ML | B11: 1120 | C11: 14.22293 | D11: 59.266667 | E11: 3 | F11: 436 | G11: 0.31001805 | H11: ⚠ Risco Estoque | I11: 10
A12: BL AMBAR-FOSSIL 5ML | B12: 1104 | C12: 13.93959 | D12: 40 | E12: 1 | F12: 451 | G12: 0.20151025 | H12: ⚠ Risco Estoque | I12: 5
A13: BL GLICINIA 5ML | B13: 1079 | C13: 35.873982 | D13: 110.55254 | E13: 59 | F13: 315 | G13: 0.22550287 | H13: ✓ Disponível | I13: 5
A14: BL INCENSO 5ML | B14: 873 | C14: 20.049907 | D14: 77.020408 | E14: 98 | F14: 308 | G14: 0.28968059 | H14: ✓ Disponível | I14: 5
A15: BL LIRIO-DO-VALE 5ML | B15: 1105 | C15: 28.792117 | D15: 85.352402 | E15: 204 | F15: 135 | G15: 0.21266775 | H15: ✓ Disponível | I15: 5
A16: BL MADRESSILVA 5ML | B16: 1090 | C16: 21.59389 | D16: 88.433333 | E16: 72 | F16: 311 | G16: 0.3058173 | H16: ✓ Disponível | I16: 5
A17: BL MELISSA 5ML | B17: 839 | C17: 8.82959 | D17: 27.60119 | E17: 336 | F17: 165 | G17: 0.23010112 | H17: ✓ Disponível | I17: 5
A18: BL MUSK 5ML | B18: 1375 | C18: 16.40659 | D18: 85 | E18: 1 | F18: 442 | G18: 0.35698129 | H18: ⚠ Risco Estoque | I18: 5
... A187: EXC OE SALSA FOLHAS GT BRASIL 10ML (GOURMET) | B187: 1976 | C187: 12.83139 | D187: 53.95 | E187: 10 | F187: 399 | G187: 0.31216145 | H187: ✓ Disponível | I187: 10
A188: EXC OE SALSA FOLHAS GT EUA 5ML | B188: 2190 | C188: 7.09959 | D188: 0 | E188: 0 | F188: NOVO | G188: 0 | H188: ⚠ Risco Estoque | I188: 5
A189: EXC OE SALVIA TRILOBA CO2-TO GT TURQUIA 5ML | B189: 2109 | C189: 7.48259 | D189: 30.47037 | E189: 27 | F189: 388 | G189: 0.30443062 | H189: ✓ Disponível | I189: 5
A190: EXC OE SALVIA-BRANCA GT EUA 5ML | B190: 973 | C190: 1.26959 | D190: 106.4 | E190: 2 | F190: 413 | G190: 0.53806776 | H190: ⚠ Risco Estoque | I190: 5
A191: EXC OE SALVIA-ESCLAREIA GT EUA 5ML | B191: 1161 | C191: 15.529044 | D191: 74.028974 | E191: 78 | F191: 236 | G191: 0.34023019 | H191: ✓ Disponível | I191: 5
A192: EXC OE SEGURELHA GT ITALIA 5ML | B192: 2080 | C192: 8.14479 | D192: 27 | E192: 1 | F192: 454 | G192: 0.24834111 | H192: ⚠ Risco Estoque | I192: 5
A193: EXC OE SEMPRE-VIVA IMMORTELLE GT BOSNIA 5ML | B193: 773 | C193: 28.793859 | D193: 158.57311 | E193: 61 | F193: 130 | G193: 0.36841903 | H193: ✓ Disponível | I193: 5
A194: EXC OE SEMPRE-VIVA-DAS-AREIAS 10 GT PORTUGAL | B194: 2177 | C194: 8.53836 | D194: 0 | E194: 0 | F194: 473 | G194: 0 | H194: ⚠ Risco Estoque | I194: 10
A195: EXC OE SHISO GT JAPAO 5ML | B195: 978 | C195: 58.34459 | D195: 207.27417 | E195: 12 | F195: 348 | G195: 0.2685149 | H195: ✓ Disponível | I195: 5
A196: EXC OE TAGETES GT MADAGASCAR 10ML | B196: 919 | C196: 31.85559 | D196: 0 | E196: 0 | F196: 490 | G196: 0 | H196: ⚠ Risco Estoque | I196: 10
A197: EXC OE TANA GT MADAGASCAR 10ML | B197: 2098 | C197: 6.17959 | D197: 35.026667 | E197: 9 | F197: 412 | G197: 0.37357471 | H197: ⚠ Risco Estoque | I197: 10
A198: EXC OE TANACETO-AZUL GT MARROCOS 5ML | B198: 902 | C198: 44.55959 | D198: 155.98074 | E198: 27 | F198: 196 | G198: 0.26432633 | H198: ✓ Disponível | I198: 5
A199: EXC OE TEA TREE LIMAO GT AUSTRALIA 5ML | B199: 2159 | C199: 12.09749 | D199: 39.966667 | E199: 15 | F199: 404 | G199: 0.24731051 | H199: ✓ Disponível | I199: 5
A200: EXC OE TOMILHO QT BORNEOL GT MARROCOS 10ML | B200: 967 | C200: 27.27729 | D200: 107.29889 | E200: 9 | F200: 383 | G200: 0.29578218 | H200: ✓ Disponível | I200: 10
... A305: OE ALECRIM QT CANFORA GT ESPANHA 50ML | B305: 943 | C305: 19.81709 | D305: 126.12719 | E305: 167 | F305: 62 | G305: 0.39288011 | H305: ✓ Disponível | I305: 50
A306: OE ALECRIM QT MIRCENO GT BRASIL 5ML | B306: 2198 | C306: 6.84074 | D306: 0 | E306: 0 | F306: NOVO | G306: 0 | H306: ⚠ Risco Estoque | I306: 5
A307: OE ALECRIM QT VERBENONA GT MALAWI 5ML | B307: 1144 | C307: 8.84119 | D307: 41.350303 | E307: 99 | F307: 243 | G307: 0.33618802 | H307: ✓ Disponível | I307: 5
A308: OE ALECRIM-DO-CAMPO GT BRASIL 5ML | B308: 1149 | C308: 10.42959 | D308: 46.878519 | E308: 135 | F308: 174 | G308: 0.32751878 | H308: ✓ Disponível | I308: 5
A309: OE ALECRIM-PIMENTA GT BRASIL 10ML | B309: 1373 | C309: 7.98629 | D309: 41.6 | E309: 6 | F309: 420 | G309: 0.35802187 | H309: ⚠ Risco Estoque | I309: 10
A310: OE ALECRIM-SELVAGEM GT AFRICA-DO-SUL 5ML | B310: 1152 | C310: 25.410243 | D310: 84.2776 | E310: 25 | F310: 354 | G310: 0.24849352 | H310: ✓ Disponível | I310: 5
A311: OE AMAZONGRASS GT BRASIL 5ML | B311: 2197 | C311: 2.87644 | D311: 0 | E311: 0 | F311: NOVO | G311: 0 | H311: ⚠ Risco Estoque | I311: 5
A312: OE AMENDOAS AMARGAS GT EUA 10ML | B312: 938 | C312: 12.23269 | D312: 39.6 | E312: 3 | F312: 288 | G312: 0.24109369 | H312: ✓ Disponível | I312: 10
A313: OE ANIS-ESTRELADO GT CHINA 10ML | B313: 705 | C313: 7.773601 | D313: 34.102735 | E313: 457 | F313: 101 | G313: 0.32205345 | H313: ✓ Disponível | I313: 10
A314: OE ARBORVITAE / CEDRO-VERMELHO GT EUA 10ML | B314: 931 | C314: 33.730918 | D314: 189.11538 | E314: 13 | F314: 329 | G314: 0.37163843 | H314: ✓ Disponível | I314: 10
A315: OE BALSAMO-DO-PERU GT PERU 5ML | B315: 1167 | C315: 10.44459 | D315: 42.413684 | E315: 76 | F315: 262 | G315: 0.30374481 | H315: ✓ Disponível | I315: 5
A316: OE BERGAMOTA GT BRASIL 10ML | B316: 856 | C316: 6.74959 | D316: 41.338802 | E316: 1452 | F316: 24 | G316: 0.38672507 | H316: ✓ Disponível | I316: 10
A317: OE BERGAMOTA GT COSTA DO MARFIM 10ML | B317: 937 | C317: 15.76942 | D317: 72.355036 | E317: 137 | F317: 138 | G317: 0.33205498 | H317: ✓ Disponível | I317: 10
A318: OE BERGAMOTA GT ITALIA 10ML | B318: 883 | C318: 11.82901 | D318: 64.817341 | E318: 173 | F318: 300 | G318: 0.36750239 | H318: ✓ Disponível | I318: 10
A319: OE BERGAMOTA LFC GT CHINA / ITALIA 10ML | B319: 749 | C319: 11.909494 | D319: 65.377393 | E319: 399 | F319: 50 | G319: 0.36783468 | H319: ✓ Disponível | I319: 10
A320: OE BETULA DEFUMADA GT RUSSIA 5ML | B320: 1143 | C320: 10.04959 | D320: 76.425203 | E320: 123 | F320: 122 | G320: 0.41850424 | H320: ✓ Disponível | I320: 5
A321: OE BETULA-DOCE GT EUA 10ML | B321: 933 | C321: 18.42799 | D321: 125.8 | E321: 5 | F321: 214 | G321: 0.40351359 | H321: ✓ Disponível | I321: 10
A322: OE BREU GT BRASIL 5ML | B322: 863 | C322: 14.44959 | D322: 46.401878 | E322: 772 | F322: 59 | G322: 0.23859903 | H322: ✓ Disponível | I322: 5
A323: OE BREU-PRETO GT BRASIL 5ML | B323: 1139 | C323: 13.26959 | D323: 33.397674 | E323: 86 | F323: 210 | G323: 0.15267922 | H323: ✓ Disponível | I323: 5
... A377: OE FUNCHO-AMARGO GT BULGARIA 10ML | B377: 1109 | C377: 8.06199 | D377: 40.359375 | E377: 32 | F377: 281 | G377: 0.35024492 | H377: ✓ Disponível | I377: 10
A378: OE FUNCHO-DOCE (PLANTA) GT BRASIL 5ML | B378: 2236 | C378: 5.34959 | D378: 0 | E378: 0 | F378: NOVO | G378: 0 | H378: ⚠ Risco Estoque | I378: 5
A379: OE FUNCHO-DOCE GT BRASIL 10ML | B379: 840 | C379: 12.08939 | D379: 0 | E379: 0 | F379: 294 | G379: 0 | H379: ✓ Disponível | I379: 10
A380: OE GALBANO GT IRA 5ML | B380: 1051 | C380: 17.56974 | D380: 52.328571 | E380: 7 | F380: 425 | G380: 0.21424193 | H380: ⚠ Risco Estoque | I380: 5
A381: OE GENGIBRE CO2-SE GT INDIA 5ML | B381: 864 | C381: 16.54459 | D381: 66.822963 | E381: 135 | F381: 304 | G381: 0.30241161 | H381: ✓ Disponível | I381: 5
A382: OE GENGIBRE CO2-TO GT INDIA 5ML | B382: 1150 | C382: 8.48511 | D382: 89.838 | E382: 20 | F382: 333 | G382: 0.45555099 | H382: ✓ Disponível | I382: 5
A383: OE GENGIBRE GT CHINA 10ML | B383: 720 | C383: 10.895652 | D383: 59.880193 | E383: 311 | F383: 73 | G383: 0.36804247 | H383: ✓ Disponível | I383: 10
A384: OE GERANIO QT CITRONELOL GT CHINA 10ML | B384: 2155 | C384: 15.03619 | D384: 89 | E384: 3 | F384: 416 | G384: 0.38105404 | H384: ⚠ Risco Estoque | I384: 10
A385: OE GERANIO QT CITRONELOL GT EGITO / CHINA 10ML | B385: 751 | C385: 15.40759 | D385: 53.235216 | E385: 1434 | F385: 25 | G385: 0.26057523 | H385: ✓ Disponível | I385: 10
A386: OE GERANIO QT GERANIOL GT BRASIL 10ML | B386: 896 | C386: 10.34872 | D386: 0 | E386: 0 | F386: 295 | G386: 0 | H386: ✓ Disponível | I386: 10
A387: OE GERANIO-ROSA GT BRASIL 5ML | B387: 874 | C387: 17.95514 | D387: 57.612425 | E387: 536 | F387: 65 | G387: 0.23834605 | H387: ✓ Disponível | I387: 5
A388: OE GERANIO-ROSA GT INDIA 5ML | B388: 983 | C388: 9.20769 | D388: 56.029238 | E388: 223 | F388: 108 | G388: 0.38566277 | H388: ✓ Disponível | I388: 5
A389: OE GRAPEFRUIT LFC GT BRASIL 10ML | B389: 1115 | C389: 5.952007 | D389: 86.505517 | E389: 29 | F389: 249 | G389: 0.48119506 | H389: ✓ Disponível | I389: 10
A390: OE GRAPEFRUIT-ROSA GT BRASIL 10ML | B390: 878 | C390: 6.101617 | D390: 30.934164 | E390: 317 | F390: 132 | G390: 0.35275475 | H390: ✓ Disponível | I390: 10
... A440: OE LOURO FOLHAS GT TURQUIA 10ML | B440: 728 | C440: 11.39139 | D440: 59.210417 | E440: 408 | F440: 57 | G440: 0.35761172 | H440: ✓ Disponível | I440: 10
A441: OE MACACAPORANGA GT BRASIL 5ML | B441: 2235 | C441: 3.00609 | D441: 0 | E441: 0 | F441: NOVO | G441: 0 | H441: ⚠ Risco Estoque | I441: 5
A442: OE MACELA-DO-CAMPO 10 GT BRASIL 10ML | B442: 729 | C442: 5.70743 | D442: 68.833333 | E442: 36 | F442: 321 | G442: 0.46708334 | H442: ✓ Disponível | I442: 10
A443: OE MANDARINA LFC GT BRASIL 10ML | B443: 1110 | C443: 4.03015 | D443: 30.185161 | E443: 186 | F443: 160 | G443: 0.41648572 | H443: ✓ Disponível | I443: 10
A444: OE MANDARINA-AMARELA GT BRASIL 10ML | B444: 955 | C444: 7.10419 | D444: 0 | E444: 0 | F444: 297 | G444: 0 | H444: ✓ Disponível | I444: 10
A445: OE MANDARINA-VERDE GT BRASIL 10ML | B445: 730 | C445: 4.841342 | D445: 23.675385 | E445: 260 | F445: 169 | G445: 0.34551158 | H445: ✓ Disponível | I445: 10
A446: OE MANDARINA-VERMELHA GT BRASIL 10ML | B446: 1162 | C446: 5.11033 | D446: 28.658743 | E446: 175 | F446: 185 | G446: 0.37168339 | H446: ✓ Disponível | I446: 10
A447: OE MANJERICAO-DOCE GT BRASIL 5ML | B447: 2185 | C447: 4.17112 | D447: 0 | E447: 0 | F447: 184 | G447: 0 | H447: ✓ Disponível | I447: 5
A448: OE MANJERICAO-LIMAO QT CITRAL GT EUA 5ML | B448: 2108 | C448: 11.489605 | D448: 42.524722 | E448: 72 | F448: 264 | G448: 0.27981352 | H448: ✓ Disponível | I448: 5
A449: OE MANJERONA-DOCE GT EGITO / HUNGRIA 5ML | B449: 862 | C449: 7.596365 | D449: 39.994366 | E449: 142 | F449: 178 | G449: 0.36006412 | H449: ✓ Disponível | I449: 5
A450: OE MANJERONA-SILVESTRE GT ESPANHA 10ML | B450: 1915 | C450: 18.09519 | D450: 120 | E450: 1 | F450: 439 | G450: 0.39920675 | H450: ⚠ Risco Estoque | I450: 10
A451: OE MAY CHANG / LITSEA CUBEBA GT CHINA 10ML | B451: 923 | C451: 7.59748 | D451: 37.944244 | E451: 344 | F451: 111 | G451: 0.34977253 | H451: ✓ Disponível | I451: 10
A452: OE MIRRA GT ETIOPIA 5ML | B452: 813 | C452: 30.81899 | D452: 97.96063 | E452: 127 | F452: 150 | G452: 0.23539412 | H452: ✓ Disponível | I452: 5
A453: OE MURTA QT CINEOL GT ESPANHA 5ML | B453: 820 | C453: 17.26034 | D453: 46.055629 | E453: 151 | F453: 195 | G453: 0.17522844 | H453: ✓ Disponível | I453: 5
... A466: OE OREGANO-DA-ESPANHA GT ALBANIA 5ML | B466: 1126 | C466: 7.93039 | D466: 59.827273 | E466: 44 | F466: 325 | G466: 0.41744524 | H466: ✓ Disponível | I466: 5
A467: OE OREGANO-DA-SIRIA GT TURQUIA 5ML | B467: 2191 | C467: 8.29959 | D467: 0 | E467: 0 | F467: NOVO | G467: 0 | H467: ⚠ Risco Estoque | I467: 5
A468: OE OREGANO-DO-MEDITERRANEO GT TURQUIA 5ML | B468: 2192 | C468: 8.29971 | D468: 0 | E468: 0 | F468: 310 | G468: 0 | H468: ✓ Disponível | I468: 5
A469: OE OREGANO-EXTRA GT HUNGRIA 10ML | B469: 1005 | C469: 10.63959 | D469: 0 | E469: 0 | F469: 299 | G469: 0 | H469: ✓ Disponível | I469: 10
A470: OE OREGANO-EXTRA GT HUNGRIA 5ML | B470: 2193 | C470: 5.95459 | D470: 0 | E470: 0 | F470: NOVO | G470: 0 | H470: ⚠ Risco Estoque | I470: 5
A471: OE PALMAROSA GT BRASIL 10ML | B471: 732 | C471: 7.40509 | D471: 37.392831 | E471: 717 | F471: 52 | G471: 0.35196498 | H471: ✓ Disponível | I471: 10
A472: OE PATCHOULI CLARO GT INDONESIA 10ML | B472: 737 | C472: 10.19632 | D472: 50.809632 | E472: 489 | F472: 56 | G472: 0.34932309 | H472: ✓ Disponível | I472: 10
A473: OE PATCHOULI ESCURO GT INDONESIA 10ML | B473: 731 | C473: 14.491978 | D473: 40.27094 | E473: 1032 | F473: 37 | G473: 0.19013807 | H473: ✓ Disponível | I473: 10
A474: OE PAU-ROSA GT BRASIL 5ML | B474: 2241 | C474: 1.34959 | D474: 0 | E474: 0 | F474: NOVO | G474: 0 | H474: ⚠ Risco Estoque | I474: 5
A475: OE PAU-SANTO MADEIRA GT EQUADOR 5ML | B475: 956 | C475: 33.11429 | D475: 76.790541 | E475: 111 | F475: 198 | G475: 0.11877123 | H475: ✓ Disponível | I475: 5
A476: OE PETITGRAIN-DE-LARANJA GT PARAGUAI 10ML | B476: 766 | C476: 8.48749 | D476: 35.832868 | E476: 516 | F476: 86 | G476: 0.31313674 | H476: ✓ Disponível | I476: 10
A477: OE PIMENTA-MALAGUETA CO2-TO GT INDIA 10ML | B477: 928 | C477: 20.37989 | D477: 82 | E477: 2 | F477: 438 | G477: 0.30146476 | H477: ⚠ Risco Estoque | I477: 10
A478: OE PIMENTA-PRETA GT INDIA 5ML | B478: 734 | C478: 5.680686 | D478: 41.238511 | E478: 235 | F478: 119 | G478: 0.41224803 | H478: ✓ Disponível | I478: 5
A479: OE PINDAIBA FRUTOS GT BRASIL 5ML | B479: 2154 | C479: 22.18109 | D479: 79.957716 | E479: 162 | F479: 131 | G479: 0.27258975 | H479: ✓ Disponível | I479: 5
A480: OE PINHEIRO-SILVESTRE GT BULGARIA 10ML | B480: 753 | C480: 11.997423 | D480: 46.320736 | E480: 299 | F480: 118 | G480: 0.29099239 | H480: ✓ Disponível | I480: 10
A481: OE PITANGA FOLHAS GT BRASIL 5ML | B481: 1216 | C481: 18.76959 | D481: 61.51129 | E481: 186 | F481: 154 | G481: 0.24485943 | H481: ✓ Disponível | I481: 5
A482: OE PRIPRIOCA-DA-INDIA GT INDIA 5ML | B482: 2084 | C482: 16.14244 | D482: 51.706667 | E482: 90 | F482: 254 | G482: 0.23780737 | H482: ✓ Disponível | I482: 5
A483: OE RAVENSARA-ANISATA GT MADAGASCAR 10ML | B483: 917 | C483: 12.81519 | D483: 54.13 | E483: 92 | F483: 242 | G483: 0.31325162 | H483: ✓ Disponível | I483: 10
A484: OE RAVENSARA-AROMATICA GT MADAGASCAR 5ML | B484: 879 | C484: 13.81589 | D484: 0 | E484: 0 | F484: 225 | G484: 0 | H484: ✓ Disponível | I484: 5
A485: OE RAVINTSARA GT MADAGASCAR 5ML | B485: 884 | C485: 4.712322 | D485: 0 | E485: 0 | F485: 226 | G485: 0 | H485: ✓ Disponível | I485: 5
A486: OE ROSA-DE-DAMASCO 10 GT MARROCOS 10ML | B486: 735 | C486: 12.328082 | D486: 63.580378 | E486: 1269 | F486: 15 | G486: 0.35610241 | H486: ✓ Disponível | I486: 10
...

Sheet Base cadastro MP
A1: Código MP | B1: Nome MP | C1: Und | D1: Fabricante | E1: Classificação | F1: Qtd Min | G1: Preço Custo Real
A2: 1334 | B2: ABS ACACIA DOCE | C2: KG | D2: LIBERTY NATURAL | E2: ABSOLUTOS. | F2: 0 | G2: 17584
A3: 716 | B3: ABS ACACIA MIMOSA ABSOLUTO GT FRANÇA | C3: KG | D3: THE PERFUMERY | E3: ABSOLUTOS. | F3: 0.113 | G3: 4280.09
A4: 1333 | B4: ABS AÇAFRAO GT FRANÇA | C4: KG | D4: LIBERTY NATURAL | E4: ABSOLUTOS. | F4: 0 | G4: 11298
A5: 1463 | B5: ABS AÇAFROA (CÁRTAMO) GT INDIA | C5: ML | D5: LIBERTY NATURAL | E5: ABSOLUTOS. | F5: 0 | G5: 6.58
A6: 1459 | B6: ABS ALGAS MARINHAS | C6: KG | D6: NORFOLK | E6: OLEO ESSENCIAL | F6: 0 | G6: 37469.65
A7: 557 | B7: ABS AMBAR ESTORAQUE | C7: KG | D7: INTERLINK | E7: ABSOLUTOS. | F7: 0 | G7: 1042.22
A8: 1465 | B8: ABS ANGELICA RAIZES | C8: KG | D8: IMPORTADO | E8: ABSOLUTOS. | F8: 0 | G8: 12155
A9: 1466 | B9: ABS ARNICA MONTANA GT FRANÇA | C9: KG | D9: LIBERTY NATURAL | E9: ABSOLUTOS. | F9: 0 | G9: 14097
A10: 2656 | B10: ABS AZEVEM SECO GT FRANÇA | C10: KG | D10: LIBERTY NATURAL | E10: ABSOLUTOS. | F10: 0 | G10: 12955
A11: 1331 | B11: ABS BALSAMO DO PERU ABSOLUTO | C11: KG | D11: INTERLINK | E11: ABSOLUTOS. | F11: 1 | G11: 714.76
A12: 1467 | B12: ABS BALSAMO DO TOLU ABSOLUTO | C12: KG | D12: LIBERTY NATURAL | E12: ABSOLUTOS. | F12: 0 | G12: 991.08
A13: 1468 | B13: ABS BAUNILHA | C13: KG | D13: GLAMIR | E13: ABSOLUTOS. | F13: 0.5 | G13: 38230
... A846: 1894 | B846: INS ZOOMZYME GLU10 50G | C846: G | D846: VIA FARMA | E846: COSMETICOS | F846: 0 | G846: 275
A847: 1111111 | B847: KIT ESSENCIALMENTE YOGA - AILLA PACHECO | F847: 0 | G847: 0
A848: 2222222 | B848: KIT MAHA LILAH 2ª EDICAO | F848: 0 | G848: 23.91
A849: 3333333 | B849: KIT S.U.A.VI | F849: 0 | G849: 31.43
A850: 4444444 | B850: KIT VIBRACAO - ESSENCIA DA CRIACAO/MUSICA | F850: 0 | G850: 12.9
A851: 105 | B851: LECITINA DE GIRASSOL 1KG | C851: UN | D851: ADICEL | E851: INSUMOS | F851: 0 | G851: 189.9
A852: 23 | B852: LECITINA DE SOJA LIQUIDA 1KG | C852: UN | D852: ADICEL | E852: INSUMOS | F852: 0 | G852: 14.86
A853: 1080 | B853: LEITE DE COCO EM PO VEGANO 5KG | C853: UN | D853: ADEL COCO BRASIL | E853: PRODUÇÃO | F853: 0 | G853: 212.77
A854: 1081 | B854: LEITE DE COCO EM PO VEGANO LF 5KG | C854: UN | D854: ADEL COCO BRASIL | E854: PRODUÇÃO | F854: 0 | G854: 180.8
A855: 24 | B855: LEITE EM PO PIRACANJUBA | C855: KG | D855: OESA COMERCIO | E855: INSUMOS | F855: 0 | G855: 49
A856: 34 | B856: LICOR DE CACAU | C856: KG | D856: OUTROS | E856: INSUMOS | F856: 0 | G856: 27.6
A857: 793 | B857: LIFE SDHA S10-P2000 (OMEGA 3) | C857: KG | D857: UNIVAR | E857: INSUMOS | F857: 0 | G857: 353.32
A858: 27 | B858: LIMÃO TAHITI GRANULADO 0,4 A 2,0MM 20KG | C858: SC | D858: MACCA DESIDRATADOS | E858: INSUMOS | F858: 0 | G858: 662.6
A859: 5555555 | B859: LIVRO A ALQUIMIA DA MENOPAUSA | F859: 208 | G859: 10.45
A860: 6666666 | B860: LIVRO A BIBLIA DOS OLEOS ESSENCIAIS | F860: 0 | G860: 32.54
A861: 7777777 | B861: LIVRO A BIBLIA PARA TRATAMENTO DE DORES COM | F861: 500 | G861: 24.2
A862: 8888888 | B862: LIVRO A CURA PELO IODO | F862: 0 | G862: 11.15
A863: 9999999 | B863: LIVRO A QUIMICA DOS OLEOS AROMATERAPEUTICOS | F863: 0 | G863: 22
A864: 11111110 | B864: LIVRO A TERAPIA DO MAGNESIO TRANSDERMICO | F864: 108 | G864: 31.04
A865: 12222221 | B865: LIVRO A TIREOIDITE HASHIMOTO | F865: 0 | G865: 13.85
A866: 13333332 | B866: LIVRO A VITAMINA D3 | F866: 0 | G866: 9.75
A867: 14444443 | B867: LIVRO A VITAMINA K2 E O PARADOXO DO CALCIO | F867: 0 | G867: 8.85
A868: 15555554 | B868: LIVRO ALIENIGENAS DO PASSADO SERIE DO HISTORY | F868: 0 | G868: 15.15
A869: 16666665 | B869: LIVRO ALQUIMIA DOS AROMAS PARA A JUVENTUDE | F869: 0 | G869: 8.96
A870: 17777776 | B870: LIVRO ALZHEIMER E O OLFATO | F870: 0 | G870: 23.64
... A928: 82222214 | B928: LIVRO TUDO SOBRE VIRUS | F928: 0 | G928: 10.95
A929: 3461 | B929: MALTITOL CRISTAL ADOÇANTE NATURAL | C929: KG | D929: OUTROS | E929: INSUMOS | F929: 0 | G929: 37.9
A930: 8 | B930: MANTEIGA DE CACAU DESODORIZADA ORGANICA | C930: KG | D930: IBC | E930: INSUMOS | F930: 0 | G930: 58
A931: 1930 | B931: MERCOTECH DESIFETANTE BIG 5L | C931: BB | D931: CONFIAMIX | E931: OBJETOS/MOVEIS/UTENSILIOS | F931: 0 | G931: 598.78
A932: 139 | B932: MP HIDROLATO DE ALECRIM | C932: LT | D932: AKÃ OLEOS ESSENCIAIS | E932: INSUMOS | F932: 0 | G932: 33
A933: 129 | B933: MP HIDROLATO DE GERANIO | C933: LT | D933: AKÃ OLEOS ESSENCIAIS | E933: INSUMOS | F933: 0 | G933: 33
A934: 140 | B934: MP HIDROLATO DE TEA TREE | C934: LT | D934: AKÃ OLEOS ESSENCIAIS | E934: INSUMOS | F934: 0 | G934: 33
A935: 4058 | B935: MP OE ALECRIM QT MIRCENO GT BRASIL | C935: LT | D935: AROMACH INGREDIENTES | E935: INSUMOS | F935: 0 | G935: 1098.23
A936: 4065 | B936: MP OE AMAZONGRASS GT BRASIL | C936: KG | D936: THERRA AROMAS E SABORES | E936: INSUMOS | F936: 0 | G936: 305.37
A937: 370 | B937: MP OE CENOURA SEMENTES | C937: UND | D937: MENTHOLINDIA | E937: INSUMOS | F937: 1 | G937: 953.8
A938: 4084 | B938: MP OE FUNCHO-DOCE PLANTA GT BRASIL | C938: LT | D938: AKÃ OLEOS ESSENCIAIS | E938: INSUMOS | F938: 1 | G938: 800
A939: 4078 | B939: MP OE MACACAPORANGA GT BRASIL 5 ML | C939: KG | D939: AROMACH INGREDIENTES | E939: INSUMOS | F939: 0 | G939: 331.3
A940: 4090 | B940: MP OR ALECRIM GT INDIA | C940: UND | D940: MENTHOLINDIA | E940: INSUMOS | F940: 1 | G940: 474.32
... A2584: 31 | B2584: UVA PASSAS ESCURA 5KG | C2584: KG | D2584: BRASIL FRUTT | E2584: INSUMOS | F2584: 0 | G2584: 14.2

Sheet Check_Retirada
A1: Código Laszlo | B1: Nome do Produto | C1: Ranking | D1: Preço Custo | E1: Estoque | F1: Status
A2: 776 | B2: ARGILA BRANCA 230G | C2: Retirar de linha | D2: 0 | E2: 0 | F2: ⛔ RETIRADA DE LINHA
A3: 775 | B3: ARGILA PRETA 350G | C3: Retirar de linha | D3: 0 | E3: 0 | F3: ⛔ RETIRADA DE LINHA
A4: 777 | B4: ARGILA VERDE 350G | C4: Retirar de linha | D4: 0 | E4: 0 | F4: ⛔ RETIRADA DE LINHA
A5: 774 | B5: ARGILA VERMELHA 350G | C5: Retirar de linha | D5: 0 | E5: 0 | F5: ⛔ RETIRADA DE LINHA
A6: 1107 | B6: CO ALOEGEL ESFOLIANTE 200G | C6: Retirar de linha | D6: 20.549206 | E6: 0 | F6: ⛔ RETIRADA DE LINHA
A7: 746 | B7: CO GEL NEUTRO 1KG | C7: Retirar de linha | D7: 25.5948 | E7: 75 | F7: ⛔ RETIRADA DE LINHA
A8: 960 | B8: CO GEL NEUTRO 200G | C8: Retirar de linha | D8: 13.21162 | E8: 4 | F8: ⛔ RETIRADA DE LINHA
A9: 1108 | B9: CO MY CREAM PELES NORMAIS E OLEOSAS 1KG | C9: Retirar de linha | D9: 66.7499 | E9: 0 | F9: ⛔ RETIRADA DE LINHA
A10: 1142 | B10: OG MARACUJA 500ML | C10: Retirar de linha | D10: 21.067935 | E10: 0 | F10: ⛔ RETIRADA DE LINHA
A11: 1062 | B11: CHOCOLATE AO LEITE COM OMEGA 3 40 80G | C11: 186 | D11: 3.6 | E11: 12 | F11: ⛔ RETIRADA DE LINHA
A12: 2050 | B12: CHOCOLATE AO LEITE COM ÔMEGA 3 5G | C12: 516 | D12: 0.2389826 | E12: 0 | F12: ⛔ RETIRADA DE LINHA
A13: 1063 | B13: CHOCOLATE BRANCO BETULA DEFUMADA E BARU 40 | C13: 422 | D13: 7.21 | E13: 0 | F13: ⛔ RETIRADA DE LINHA
A14: 2052 | B14: CHOCOLATE BRANCO DE PACOCA 5G | C14: 517 | D14: 0.84187725 | E14: 0 | F14: ⛔ RETIRADA DE LINHA
A15: 2049 | B15: CHOCOLATE BRANCO DE ROSAS E HIBISCO 5G | C15: 518 | D15: 0.890862 | E15: 0 | F15: ⛔ RETIRADA DE LINHA
A16: 829 | B16: CHOCOLATE BRANCO MOUSSE DE LIMAO-SICILIANO 42 | C16: 149 | D16: 7.55 | E16: 0 | F16: ⛔ RETIRADA DE LINHA
A17: 1075 | B17: CHOCOLATE BRANCO ROSAS COM FLORES HIBISCO 44 | C17: 519 | D17: 7.12 | E17: 0 | F17: ⛔ RETIRADA DE LINHA
A18: 1134 | B18: CHOCOLATE BRANCO VEGANO JASMIM COM LEITE 42 | C18: 520 | D18: 6.82 | E18: 0 | F18: ⛔ RETIRADA DE LINHA
A19: 2055 | B19: CHOCOLATE CANELA COM CAFE 60 80G | C19: 217 | D19: 2.54 | E19: 0 | F19: ⛔ RETIRADA DE LINHA
A20: 826 | B20: CHOCOLATE GOLDEN CHAI 42 80G | C20: 201 | D20: 6.24 | E20: 0 | F20: ⛔ RETIRADA DE LINHA
A21: 2047 | B21: CHOCOLATE GOLDEN CHAI 5G | C21: 521 | D21: 1.0444956 | E21: 0 | F21: ⛔ RETIRADA DE LINHA
A22: 2048 | B22: CHOCOLATE LAVANDA FINA BULGARIA E AMENDOAS 5G | C22: 522 | D22: 0.89917811 | E22: 0 | F22: ⛔ RETIRADA DE LINHA
... A49: 1432 | B49: EXTRATO QE SALVIA 10ML | C49: 567 | D49: 2.61139 | E49: 0 | F49: ⛔ RETIRADA DE LINHA

Sheet Parâmetros v3
A1: DOMME MOTOR v3 — PARÂMETROS GLOBAIS
A3: MARGENS E TAXAS
A4: MIL — Margem Industrial Laszlo | B4: 0.4
A5: MD — Margem Comercial DOMME | B5: 0.2
A6: Selo Laszlo | B6: 0.03
A7: Tier 1 — Markup (≤500 un/lote) | B7: 0.2
A8: Tier 2 — Markup (501-2000 un/lote) | B8: 0.1
A9: Tier 3 — Markup (>2000 un/lote) | B9: 0
A10: Desconto kit | B10: 0.05
A11: Embalagem kit (R$) | B11: 5.5
A13: FEES DOMME
A14: Fee Estruturação (fixo) | B14: 1500
A16: ESCALA v3
A17: Limite lote fator 2x | B17: 100
A18: Fator escala pequeno | B18: 2
A20: TRAVA LASZLO
A21: MC mínima atacado | B21: 0.2
A23: VIABILIDADE
A24: IV máximo (PFC/Varejo) | B24: 0.55
A26: EXPORTAÇÃO
A27: Markup internacional OEs | B27: 8
A29: ROI CONSERVADOR
A30: Desc. impostos+frete | B30: 0.15

Sheet Regras v3
A1: DOMME MOTOR v3 — REGRAS DE NEGÓCIO
A3: 1. INTELIGÊNCIA DE CUSTOS
A4: CVU puxado da aba "Catálogo Laszlo" (Preço Custo Real da fábrica)
A5: Lotes ≤100un: insumos de envase (frasco/tampa/gotejador) multiplicados por 2x
A6: Trava: Laszlo mantém mínimo 20% MC no atacado — alerta automático se violado
A7: SKUs em "Check_Retirada" bloqueiam o cálculo com alerta visual ⛔
A9: 2. ESTRUTURA v3
A10: Volume = por Lote/Pedido (não mais anual)
A11: Full-Service obrigatório: Kit Envase + Fee DOMME R$1.500 fixo
A12: Fee rateado por unidade: R$1.500 ÷ qtd do lote
A13: Tiers por lote: T1≤500 (+20%) | T2≤2000 (+10%) | T3>2000 (0%)
A15: 3. MÉTRICAS DE SUCESSO
... A30: Foco regulatório: Aromas Naturais / Alimentos para rapidez de mercado
